argutil/__init__.py
argutil/_arguments.py
argutil/argutil.py
atd_args_util_dev-0.0.6.dist-info/LICENSE
atd_args_util_dev-0.0.6.dist-info/METADATA
atd_args_util_dev-0.0.6.dist-info/WHEEL
atd_args_util_dev-0.0.6.dist-info/top_level.txt
atd_args_util_dev-0.0.6.dist-info/RECORD
