Metadata-Version: 2.1
Name: atd-args-util-dev
Version: 0.0.6
Summary: Reusable argument parser for Python scripts.
Home-page: https://github.com/cityofaustin/atd-data-utilities/tree/master/atd-args-util
Author: City of Austin
Author-email: transportation.data@austintexas.gov
License: UNKNOWN
Platform: UNKNOWN
Classifier: Programming Language :: Python :: 3
Classifier: License :: Public Domain
Classifier: Operating System :: OS Independent
Classifier: Development Status :: 4 - Beta
